setup.py
reductio/__init__.py
reductio/config.py
reductio/demo.py
reductio/network.py
reductio/operate.py
reductio/para_ssh.py
reductio/process.py
reductio/tasks.py
reductio.egg-info/PKG-INFO
reductio.egg-info/SOURCES.txt
reductio.egg-info/dependency_links.txt
reductio.egg-info/requires.txt
reductio.egg-info/top_level.txt