Metadata-Version: 1.0
Name: reductio
Version: 0.2.1
Summary: Map/Reduce for Fabric
Home-page: http://github.com/rspeer/reductio
Author: Rob Speer
Author-email: rspeer@mit.edu
License: AGPLv3
Keywords: mapreduce distributed fabric
Platform: UNKNOWN
